MANIFEST.in
README.txt
setup.py
Products/__init__.py
Products/__init__.pyc
Products.BugzScout.egg-info/PKG-INFO
Products.BugzScout.egg-info/SOURCES.txt
Products.BugzScout.egg-info/dependency_links.txt
Products.BugzScout.egg-info/entry_points.txt
Products.BugzScout.egg-info/namespace_packages.txt
Products.BugzScout.egg-info/not-zip-safe
Products.BugzScout.egg-info/requires.txt
Products.BugzScout.egg-info/top_level.txt
Products/BugzScout/__init__.py
Products/BugzScout/browser.py
Products/BugzScout/configure.zcml
Products/BugzScout/interfaces.py
Products/BugzScout/profiles.zcml
Products/BugzScout/scout.py
Products/BugzScout/skins.zcml
Products/BugzScout/profiles/default/metadata.xml
Products/BugzScout/profiles/default/registry.xml
Products/BugzScout/profiles/default/skins.xml
Products/BugzScout/skins/BugzScout/standard_error_message.py
Products/BugzScout/tests/__init__.py
Products/BugzScout/tests/base.py
Products/BugzScout/tests/test_scout.py
doc/changes.rst