Metadata-Version: 1.0
Name: Products.BugzScout
Version: 1.0a2
Summary: FogBugz Plone integration using BugzScout.
Home-page: https://weblion.psu.edu/
Author: WebLion Group, Penn State University
Author-email: support@weblion.psu.edu
License: GPL
Keywords: weblion fogbugz
Platform: UNKNOWN
Classifier: Framework :: Plone
Classifier: Framework :: Zope2
Classifier: Programming Language :: Python
Classifier: Intended Audience :: Developers
Classifier: Development Status :: 3 - Alpha
